nanobind/__init__.py
nanobind/__main__.py
nanobind/cmake/darwin-ld-cpython.sym
nanobind/cmake/darwin-ld-pypy.sym
nanobind/cmake/darwin-python-path.py
nanobind/cmake/nanobind-config-version.cmake
nanobind/cmake/nanobind-config.cmake
nanobind/ext/robin_map/include/tsl/robin_growth_policy.h
nanobind/ext/robin_map/include/tsl/robin_hash.h
nanobind/ext/robin_map/include/tsl/robin_map.h
nanobind/include/nanobind/eigen/dense.h
nanobind/include/nanobind/eigen/sparse.h
nanobind/include/nanobind/eval.h
nanobind/include/nanobind/intrusive/counter.h
nanobind/include/nanobind/intrusive/counter.inl
nanobind/include/nanobind/intrusive/ref.h
nanobind/include/nanobind/make_iterator.h
nanobind/include/nanobind/nanobind.h
nanobind/include/nanobind/nb_accessor.h
nanobind/include/nanobind/nb_attr.h
nanobind/include/nanobind/nb_call.h
nanobind/include/nanobind/nb_cast.h
nanobind/include/nanobind/nb_class.h
nanobind/include/nanobind/nb_defs.h
nanobind/include/nanobind/nb_descr.h
nanobind/include/nanobind/nb_enums.h
nanobind/include/nanobind/nb_error.h
nanobind/include/nanobind/nb_func.h
nanobind/include/nanobind/nb_lib.h
nanobind/include/nanobind/nb_misc.h
nanobind/include/nanobind/nb_python.h
nanobind/include/nanobind/nb_traits.h
nanobind/include/nanobind/nb_tuple.h
nanobind/include/nanobind/nb_types.h
nanobind/include/nanobind/ndarray.h
nanobind/include/nanobind/operators.h
nanobind/include/nanobind/stl/array.h
nanobind/include/nanobind/stl/bind_map.h
nanobind/include/nanobind/stl/bind_vector.h
nanobind/include/nanobind/stl/chrono.h
nanobind/include/nanobind/stl/complex.h
nanobind/include/nanobind/stl/detail/chrono.h
nanobind/include/nanobind/stl/detail/nb_array.h
nanobind/include/nanobind/stl/detail/nb_dict.h
nanobind/include/nanobind/stl/detail/nb_list.h
nanobind/include/nanobind/stl/detail/nb_optional.h
nanobind/include/nanobind/stl/detail/nb_set.h
nanobind/include/nanobind/stl/detail/traits.h
nanobind/include/nanobind/stl/filesystem.h
nanobind/include/nanobind/stl/function.h
nanobind-2.9.1.dist-info/METADATA
nanobind-2.9.1.dist-info/WHEEL
nanobind-2.9.1.dist-info/licenses/LICENSE
nanobind-2.9.1.dist-info/RECORD
