Metadata-Version: 2.1
Name: nanobind
Version: 2.9.1
Summary: nanobind: tiny and efficient C++/Python bindings
Author-Email: Wenzel Jakob <wenzel.jakob@epfl.ch>
Classifier: Intended Audience :: Developers
Classifier: License :: OSI Approved :: BSD License
Classifier: Programming Language :: C++
Classifier: Programming Language :: Python :: 3 :: Only
Classifier: Programming Language :: Python :: Implementation :: CPython
Classifier: Programming Language :: Python :: Implementation :: PyPy
Classifier: Topic :: Software Development :: Libraries :: Python Modules
Classifier: Topic :: Utilities
Project-URL: Homepage, https://github.com/wjakob/nanobind
